wireguard_reconnect/__init__.py
wireguard_reconnect/__main__.py
wireguard_reconnect/parser.py
wireguard_reconnect/utils.py
wireguard_reconnect/wireguard_reconnect.py
wireguard_reconnect-1.0.7.dist-info/LICENSE
wireguard_reconnect-1.0.7.dist-info/METADATA
wireguard_reconnect-1.0.7.dist-info/WHEEL
wireguard_reconnect-1.0.7.dist-info/entry_points.txt
wireguard_reconnect-1.0.7.dist-info/top_level.txt
wireguard_reconnect-1.0.7.dist-info/zip-safe
wireguard_reconnect-1.0.7.dist-info/RECORD
