Metadata-Version: 2.1
Name: wireguard-reconnect
Version: 1.0.7
Summary: This program performs unattended handling of selected WireGuard interfaces, bringing them up and down depending on whether there is connectivity to the server or not, or simply bringing them up and keeping them up.
Home-page: https://github.com/fernandoenzo/wireguard-reconnect
Download-URL: https://github.com/fernandoenzo/wireguard-reconnect/releases
Author: Fernando Enzo Guarini
Author-email: fernandoenzo@gmail.com
Maintainer: 
Maintainer-email: 
License: AGPLv3+
Keywords: wireguard net vpn ip link ping route routing
Platform: any
Classifier: Development Status :: 5 - Production/Stable
Classifier: Environment :: Console
Classifier: Intended Audience :: End Users/Desktop
Classifier: License :: OSI Approved :: GNU Affero General Public License v3 or later (AGPLv3+)
Classifier: Natural Language :: English
Classifier: Operating System :: POSIX :: Linux
Classifier: Programming Language :: Python :: 3.7
Classifier: Programming Language :: Python :: 3.8
Classifier: Programming Language :: Python :: 3.9
Classifier: Programming Language :: Python :: 3.10
Classifier: Topic :: Communications
Classifier: Topic :: Internet
Classifier: Topic :: System :: Networking
Classifier: Topic :: Utilities
Requires-Python: >=3.7
License-File: LICENSE
